LICENSE
pynfse/__init__.py
pynfse/base/__init__.py
pynfse/base/certificate.py
pynfse/base/models.py
pynfse/base/nfse_signer.py
pynfse/base/soap_client.py
pynfse/nfse/__init__.py
pynfse/nfse/pr/__init__.py
pynfse/nfse/pr/curitiba/__init__.py
pynfse/nfse/pr/curitiba/_dsig.py
pynfse/nfse/pr/curitiba/_facade.py
pynfse/nfse/pr/curitiba/_schema.py
pynfse/nfse/pr/curitiba/comunicacao.py
pynfse/nfse/pr/curitiba/serializacao.py
pynfse-0.2.0.dist-info/LICENSE
pynfse-0.2.0.dist-info/WHEEL
pynfse-0.2.0.dist-info/METADATA
pynfse-0.2.0.dist-info/RECORD
