Metadata-Version: 2.1
Name: pynfse
Version: 0.2.0
Summary: Lib para emissão de NFSe
Home-page: https://github.com/marcelobelli/PyNFSe
License: LGPL-3.0
Keywords: nfe,nfse,nota_fiscal
Author: Marcelo Belli
Author-email: marcelo@belli.me
Requires-Python: >=3.7,<4.0
Classifier: Development Status :: 3 - Alpha
Classifier: Intended Audience :: Developers
Classifier: Intended Audience :: Other Audience
Classifier: License :: OSI Approved :: GNU Lesser General Public License v3 (LGPLv3)
Classifier: License :: OSI Approved :: GNU Lesser General Public License v3 or later (LGPLv3+)
Classifier: Natural Language :: Portuguese (Brazilian)
Classifier: Operating System :: OS Independent
Classifier: Programming Language :: Python :: 3
Classifier: Programming Language :: Python :: 3.7
Classifier: Programming Language :: Python :: 3.8
Classifier: Topic :: Office/Business :: Financial
Classifier: Topic :: Software Development :: Libraries :: Python Modules
Classifier: Topic :: Utilities
Requires-Dist: PyXB (==1.2.5)
Requires-Dist: lxml (==4.4.1)
Requires-Dist: pydantic (==1.0)
Requires-Dist: signxml (==2.6.0)
Requires-Dist: zeep (==3.4.0)
Project-URL: Repository, https://github.com/marcelobelli/PyNFSe
